benchmarking_qrc/__init__.py
benchmarking_qrc/hamiltonian.py
benchmarking_qrc/measurements.py
benchmarking_qrc/reservoir.py
benchmarking_qrc/run_memory_capacity.py
benchmarking_qrc/utils.py
benchmarking_qrc-0.0.4.dist-info/LICENSE.txt
benchmarking_qrc-0.0.4.dist-info/METADATA
benchmarking_qrc-0.0.4.dist-info/WHEEL
benchmarking_qrc-0.0.4.dist-info/top_level.txt
benchmarking_qrc-0.0.4.dist-info/RECORD
