Metadata-Version: 2.1
Name: benchmarking-qrc
Version: 0.0.4
Summary: Benchmarking QRC measures the ability to store information of 
Home-page: https://github.com/gllodra12/Benchmarking_QRC
Author: Guillem Llodrà
Author-email: gllodra1225@gmail.com
Classifier: Programming Language :: Python :: 3
Classifier: Programming Language :: Python :: 3.6
Classifier: Programming Language :: Python :: 3.7
Classifier: Programming Language :: Python :: 3.8
Classifier: Programming Language :: Python :: 3.9
License-File: LICENSE.txt
Requires-Dist: openfermion ~=1.1.0
